trashpy/__init__.py
trashpy/client_id.json
trashpy/main.py
trashpy-1.0.6.dist-info/entry_points.txt
trashpy-1.0.6.dist-info/LICENSE
trashpy-1.0.6.dist-info/WHEEL
trashpy-1.0.6.dist-info/METADATA
trashpy-1.0.6.dist-info/RECORD
